gdc/__main__.py
gdc/computestats.py
gdc/config.py
gdc/init.py
gdc/logo.png
gdc/setbuttonsclass.py
gdc/utils.py
gdc/winacceuil.py
gdc/winclassroom.py
gdc/winconfig.py
gdc/wincptces.py
gdc/winevals.py
gdc-1.3.dist-info/LICENSE.txt
gdc-1.3.dist-info/METADATA
gdc-1.3.dist-info/WHEEL
gdc-1.3.dist-info/entry_points.txt
gdc-1.3.dist-info/top_level.txt
gdc-1.3.dist-info/RECORD
